vlivepy/__init__.py
vlivepy/board.py
vlivepy/channel.py
vlivepy/comment.py
vlivepy/connections.py
vlivepy/exception.py
vlivepy/html_template.py
vlivepy/model.py
vlivepy/parser.py
vlivepy/post.py
vlivepy/router.py
vlivepy/schedule.py
vlivepy/session.py
vlivepy/upcoming.py
vlivepy/variables.py
vlivepy/video.py
vlivepy-1.1.2.dist-info/LICENSE
vlivepy-1.1.2.dist-info/METADATA
vlivepy-1.1.2.dist-info/WHEEL
vlivepy-1.1.2.dist-info/top_level.txt
vlivepy-1.1.2.dist-info/RECORD
