Metadata-Version: 2.1
Name: vlivepy
Version: 1.1.2
Summary: VLIVE(vlive.tv) parser for python
Home-page: https://github.com/box-archived/vlive-py
Author: box-archived
Author-email: box.cassette@gmail.com
License: MIT License
Platform: UNKNOWN
Requires-Dist: requests (>=2.22)
Requires-Dist: reqWrapper (>=0.2.1)
Requires-Dist: beautifulsoup4 (>=4.9.3)
